odoo/addons/purchase_products_only_from_vendors/__init__.py
odoo/addons/purchase_products_only_from_vendors/__manifest__.py
odoo/addons/purchase_products_only_from_vendors/models/__init__.py
odoo/addons/purchase_products_only_from_vendors/models/purchase_order.py
odoo/addons/purchase_products_only_from_vendors/views/purchase_order_view.xml
odoo12_addon_purchase_products_only_from_vendors-12.0.0.0.1.dist-info/METADATA
odoo12_addon_purchase_products_only_from_vendors-12.0.0.0.1.dist-info/WHEEL
odoo12_addon_purchase_products_only_from_vendors-12.0.0.0.1.dist-info/top_level.txt
odoo12_addon_purchase_products_only_from_vendors-12.0.0.0.1.dist-info/RECORD
